owned/__init__.py
owned-0.0.3.dist-info/LICENSE
owned-0.0.3.dist-info/METADATA
owned-0.0.3.dist-info/WHEEL
owned-0.0.3.dist-info/top_level.txt
owned-0.0.3.dist-info/RECORD
