Metadata-Version: 2.1
Name: owned
Version: 0.0.3
Summary: A little tool to manage secrets
Home-page: https://github.com/thorwhalen/owned
Author: Thor Whalen
License: apache-2.0
Platform: any
License-File: LICENSE
